[{"executionTime":1100,"synthesisTime":655,"roundTripTime":1687},{"executionTime":1168,"synthesisTime":663,"roundTripTime":1737},{"executionTime":1104,"synthesisTime":703,"roundTripTime":1634},{"executionTime":708,"synthesisTime":422,"roundTripTime":1226},{"executionTime":937,"synthesisTime":628,"roundTripTime":1417},{"executionTime":1220,"synthesisTime":720,"roundTripTime":1759},{"executionTime":1253,"synthesisTime":698,"roundTripTime":1835},{"executionTime":1032,"synthesisTime":646,"roundTripTime":1740},{"executionTime":886,"synthesisTime":600,"roundTripTime":1393},{"executionTime":887,"synthesisTime":607,"roundTripTime":1482}]