[{"executionTime":3494,"downloadTime":2411,"uploadTime":1083,"roundTripTime":3646},{"executionTime":1016,"downloadTime":441,"uploadTime":575,"roundTripTime":1180},{"executionTime":1295,"downloadTime":615,"uploadTime":680,"roundTripTime":1486},{"executionTime":1247,"downloadTime":466,"uploadTime":781,"roundTripTime":1517},{"executionTime":1144,"downloadTime":478,"uploadTime":666,"roundTripTime":1359},{"executionTime":1758,"downloadTime":655,"uploadTime":1103,"roundTripTime":1969},{"executionTime":1202,"downloadTime":433,"uploadTime":769,"roundTripTime":1362},{"executionTime":1104,"downloadTime":505,"uploadTime":599,"roundTripTime":1380},{"executionTime":1460,"downloadTime":585,"uploadTime":875,"roundTripTime":1697},{"executionTime":868,"downloadTime":397,"uploadTime":471,"roundTripTime":1000}]